{
  "name": "Files",
  "fullName": "Syrus.Plugins.Files",
  "author": "Vladimír Antoš",
  "version": "0.0.0.1",
  "icon": "icon.png",
  "enableHelp": false,
  "searchingConfigurations": [
    {
      "language": "en",
      "regularExpressions": [
        {
          "id": 1,
          "text": [ "^.*$" ]
        },
        {
          "id": 2,
          "text": [ "^[a-zA-Z]:\\\\[\\\\\\S|*\\S]?.*$" ]
        }
      ]
    },

    {
      "language": "cs",
      "regularExpressions": [
        {
          "id": 1,
          "text": [ "^.*$" ]
        },
        {
          "id": 2,
          "text": [ "^[a-zA-Z]:\\\\[\\\\\\S|*\\S]?.*$" ]
        }
      ]
    }
  ],
  "constants": {
    "indexedFolders": [
      {
        "folder": "C:\\Users\\vladi\\OneDrive\\Plocha",
        "exclude": "C:\\Users\\vladi\\OneDrive\\Plocha\test"
      }
    ],
    "except":  []
  }
}
